LICENSE
MANIFEST.in
README.rst
pyproject.toml
requirements.txt
setup.py
asyncify/__init__.py
asyncify/_types.py
asyncify/cls.py
asyncify/events.py
asyncify/func.py
asyncify/hybrid.py
asyncify/iterable.py
asyncify/py.typed
asyncify/sleep.py
asyncify/thread.py
asyncify_python.egg-info/PKG-INFO
asyncify_python.egg-info/SOURCES.txt
asyncify_python.egg-info/dependency_links.txt
asyncify_python.egg-info/requires.txt
asyncify_python.egg-info/top_level.txt