Metadata-Version: 2.1
Name: asyncify-python
Version: 2.0.2
Summary: A python library to make things async!
Author: The Master
License: MIT
Project-URL: GitHub, https://github.com/chawkk6404/asyncify
Project-URL: Documentation, https://asyncify.readthedocs.io/en/latest
Classifier: Development Status :: 5 - Production/Stable
Classifier: License :: OSI Approved :: MIT License
Classifier: Intended Audience :: Developers
Classifier: Natural Language :: English
Classifier: Operating System :: OS Independent
Classifier: Programming Language :: Python :: 3.7
Classifier: Programming Language :: Python :: 3.8
Classifier: Programming Language :: Python :: 3.9
Classifier: Programming Language :: Python :: 3.10
Classifier: Topic :: Internet
Classifier: Topic :: Software Development :: Libraries
Classifier: Topic :: Software Development :: Libraries :: Python Modules
Classifier: Topic :: Utilities
Classifier: Typing :: Typed
Requires-Python: >=3.7.0
Provides-Extra: docs
License-File: LICENSE
